{
"minVersion":"0.1",
"headerImage":"https://jtisvn.github.io/coverimage/jtisvnrepo.png",
"tintColor":"#FFFF99",
"tabs":[
{
"tabname":"Giới thiệu",
"views":[
{
"class":"DepictionScreenshotsView",
"screenshots":[
{
"url":"https://jtisvn.github.io/infodeb/Copylog/Screenshots/1.png",
"accessibilityText":"Screenshot"
},
{
"url":"https://jtisvn.github.io/infodeb/Copylog/Screenshots/2.png",
"accessibilityText":"Screenshot"
},
{
"url":"https://jtisvn.github.io/infodeb/Copylog/Screenshots/3.png",
"accessibilityText":"Screenshot"
},
{
"url":"https://jtisvn.github.io/infodeb/Copylog/Screenshots/4.png",
"accessibilityText":"Screenshot"
}
],
"itemCornerRadius":0,
"itemSize":"{185,400}"
},
{
"markdown":"Copylog\n\n- Là ứng dụng quản lý lịch sử bảng tạm tiện lợi trên iOS giúp bạn theo dõi lưu lại, sắp xếp, tìm kiếm và quản lý nhanh các đoạn văn bản và hình ảnh đã sao chép.\n\n- Ứng dụng hoạt động ngầm, hỗ trợ chia sẻ, xem trước liên kết, và có tính năng danh sách đen để lọc nội dung không mong muốn.\n\n- Giao diện dễ nhìn sử dụng với cử chỉ vuốt từ bàn phím và nút đọc chính tả.\n\n- Hỗ trợ thiết bị A9-A15), cả iPhone và iPad.\n\n- Hỗ trợ Dopamine & Xina.\n\n- Xem hình ảnh phía dưới để biết thêm chi tiết hơn.",
"useSpacing": false,
"class": "DepictionMarkdownView"
},
{
"spacing": 20,
"class": "DepictionSpacerView"
},
{
"class": "DepictionSeparatorView"
},
{
"class": "DepictionLabelView",
"text": "Thông tin chi tiết",
"fontWeight": "semibold",
"fontSize": 16,
"usePadding": true,
"useMargins": true,
"margins": "{10,0,8,0}"
},
{
"class": "DepictionStackView",
"orientation": "landscape",
"views": [
{
"class": "DepictionStackView",
"views": [
{
"class": "DepictionLabelView",
"text": "Tác giả",
"textColor": "#777",
"margins": "{16,0,8,0}"
},
{
"class": "DepictionLabelView",
"text": "TomT000",
"fontWeight": "semibold",
"fontSize": 16,
"usePadding": false
},
{
"class": "DepictionLabelView",
"text": "Thể loại",
"textColor": "#777",
"margins": "{16,0,8,0}"
},
{
"class": "DepictionLabelView",
"text": "Tweaks",
"fontWeight": "semibold",
"fontSize": 16,
"usePadding": false
},
{
"class": "DepictionLabelView",
"text": "Ngày cập nhật",
"textColor": "#777",
"margins": "{16,0,8,0}"
},
{
"class": "DepictionLabelView",
"text": "25/7/2025",
"fontWeight": "semibold",
"fontSize": 16,
"usePadding": false
}
]
},
{
"class": "DepictionStackView",
"views": [
{
"class": "DepictionLabelView",
"text": "Phiên bản",
"textColor": "#777",
"margins": "{16,0,8,0}"
},
{
"class": "DepictionLabelView",
"text": "17.3-end",
"fontWeight": "semibold",
"fontSize": 16,
"usePadding": false
},
{
"class": "DepictionLabelView",
"text": "Kích thước",
"textColor": "#777",
"margins": "{16,0,8,0}"
},
{
"class": "DepictionLabelView",
"text": "68 MB",
"fontWeight": "semibold",
"fontSize": 16,
"usePadding": false
},
{
"class": "DepictionLabelView",
"text": "Tương thích iOS/iPadOS",
"textColor": "#777",
"margins": "{16,0,8,0}"
},
{
"class": "DepictionLabelView",
"text": "12.0 - 16.7.11",
"fontWeight": "semibold",
"fontSize": 17,
"usePadding": false
}
]
}
]
},
{
"spacing": 25,
"class": "DepictionSpacerView"
},
{
"class":"DepictionLabelView",
"text":"Copyright © 2025 by JTISVN",
"textColor":"#999999",
"fontSize":"10.0",
"alignment":1
}
],
"class": "DepictionStackView"
},
{
"tabname":"Nhật ký thay đổi",
"views":[
{
"class":"DepictionMarkdownView",
"markdown":"### Phiên bản 17.3\n\n- Sửa lỗi\n\n- Hỗ trợ Rootfull, Rootless & Roothide Jailbreak"
}
],
"class":"DepictionStackView"
},
{
"tabname":"L.Hệ & Hỗ trợ",
"views":[
{
"class":"DepictionTableButtonView",
"title": "Paypal",
"action": "https://paypal.me/HiuKitsudo"
},
{
"class":"DepictionTableButtonView",
"title": "Ủng hộ tôi một ly cà phê",
"action": "https://jtisvn.github.io/donate/donate.html"
},
{
"class":"DepictionTableButtonView",
"title": "Nhóm Telegram",
"action": "https://t.me/jailbreaktrolliossupport"
},
{
"class":"DepictionTableButtonView",
"title": "Nhóm Facebook",
"action": "https://www.facebook.com/share/g/16wCy2KW8K/?mibextid=K35XfP"
},
{
"class":"DepictionLabelView",
"text":"Copyright © 2025 by JTISVN",
"textColor":"#999999",
"fontSize":"10.0",
"alignment":1
}
],
"class":"DepictionStackView"
}
],
"class":"DepictionTabView"
}